{"9\/6\/2016":{"3375":["tammy"],"3376":["gaz","michellemyers"],"3380":["kathyboblitt","dan","michael"],"3504":[null]},"9\/7\/2016":{"3379":["elisha"],"3382":["meg"]},"9\/11\/2016":{"3377":["hope"],"3378":["fatima","ben"],"3381":["hope","gayle","mario"]},"9\/12\/2016":{"3375":["brian"],"3376":["catherine","XXXXXXXX"],"3380":["debbi","bill","mac"],"3504":["gayle"]},"9\/13\/2016":{"3375":["sharon"],"3376":["rachelp","gaz"],"3380":["jillian","eric","dan"],"3504":["katie"]},"9\/14\/2016":{"3375":["jennifer"],"3376":["anastasia","nancy"],"3380":["rod","anastasia","nicholas"],"3504":[null]},"9\/18\/2016":{"3377":["maryking"],"3378":["fatima","gaz"],"3381":["mac","tolkien","michael"]},"9\/19\/2016":{"3379":["elisha"],"3382":["dan"]},"9\/20\/2016":{"3375":["tammy"],"3376":["michellemyers","brian"],"3380":["ted","ben","mac"],"3504":[null]},"9\/21\/2016":{"3375":["sharon"],"3376":["keithg","jillian"],"3380":["jillian","kate","hope"],"3504":[null]},"9\/25\/2016":{"3377":["megan"],"3378":["fatima","eric"],"3381":["debbi","megan","mario"]},"9\/26\/2016":{"3375":["brian"],"3376":["meg",null],"3380":["amyh","dan",null],"3504":["katie"]},"9\/27\/2016":{"3375":["kelly"],"3376":["rebecca","bill"],"3380":["patti","michael","mac"],"3504":["anne"]},"9\/28\/2016":{"3375":["rae"],"3376":["gaz","elisha"],"3380":["mac","nicholas","jillian"],"3504":[null]},"10\/2\/2016":{"3377":["maryking"],"3378":["fatima","dan"],"3381":["kathyboblitt","julia","gayle"]},"10\/3\/2016":{"3375":["sharon"],"3376":["catherine",null],"3380":["mac","bill","michael"],"3504":["katie"]},"10\/4\/2016":{"3375":["tammy"],"3376":["michellemyers","brian"],"3380":["rod","anastasia","eric"],"3504":[null]},"10\/5\/2016":{"3379":["megan"],"3382":["meg"]},"10\/9\/2016":{"3377":["hope"],"3378":["fatima","elisha"],"3381":["hope","julia","michael"]},"10\/10\/2016":{"3375":["dale"],"3376":["keithg","brian"],"3380":["mac","bill","XXXXXXXX"],"3504":["gayle"]},"10\/11\/2016":{"3375":["kate"],"3376":["rachelp","gaz"],"3380":["amyh","kate","patti"],"3504":["katie"]},"10\/12\/2016":{"3375":["brian"],"3376":["rae","gaz"],"3380":["kathyboblitt","nicholas","jillian"],"3504":["anne"]},"10\/16\/2016":{"3377":["pam"],"3378":["fatima","XXXXXXXX"],"3381":["debbi","julia","tolkien"]},"10\/17\/2016":{"3379":["megan"],"3382":["dan"]},"10\/18\/2016":{"3375":["tammy"],"3376":["rebecca","bill"],"3380":["patti","eric","kate"],"3504":[null]},"10\/19\/2016":{"3375":["kelly"],"3376":["gaz","rae"],"3380":["mac","hope",null],"3504":[null]},"10\/23\/2016":{"3377":["hope"],"3378":["fatima","elisha"],"3381":["hope","julia","michael"]},"10\/24\/2016":{"3375":["rachelp"],"3376":["meg","gayle"],"3380":["kathyboblitt","kate",null],"3504":["XXXXXXXX"]},"10\/25\/2016":{"3375":["dale"],"3376":["ted","gaz"],"3380":["ted","ben","eric"],"3504":[null]},"10\/26\/2016":{"3375":["sharon"],"3376":["anastasia","nancy"],"3380":["jillian","jacob","hope"],"3504":["anne"]},"10\/30\/2016":{"3377":["maryking"],"3378":["fatima","megan"],"3381":["rod","megan","julia"]},"11\/1\/2016":{"3375":["kelly"],"3376":["katie","bill"],"3380":["patti","nicholas","michael"],"3504":[null]},"11\/2\/2016":{"3379":["elisha"],"3382":["kathyboblitt"]},"11\/6\/2016":{"3377":["eric"],"3378":["anne","dan"],"3381":["mac","gayle","julia"]},"11\/7\/2016":{"3375":["rachelp"],"3376":["meg","dan"],"3380":["rachelp","meg",null],"3504":["katie"]},"11\/8\/2016":{"3375":["sharon"],"3376":["tevah","bill"],"3380":["rod","jacob","mac"],"3504":["anne"]},"11\/9\/2016":{"3375":["sharon"],"3376":["michellemyers","nancy"],"3380":["ted","kate","bill"],"3504":[null]},"11\/13\/2016":{"3377":["hope"],"3378":["catherine","debbi"],"3381":["hope","tolkien","michael"]},"11\/14\/2016":{"3375":["dale"],"3376":["nancy","meg"],"3380":["amyh","nicholas",null],"3504":["katie"]},"11\/15\/2016":{"3375":["tammy"],"3376":["rebecca","bill"],"3380":["patti","anastasia","dan"],"3504":["anne"]},"11\/16\/2016":{"3375":["jennifer"],"3376":["keithg","gayle"],"3380":["jillian","bill","mac"],"3504":[null]},"11\/20\/2016":{"3377":["maryking"],"3378":["eric","megan"],"3381":["mac","megan","julia"]},"11\/21\/2016":{"3379":["elisha"],"3382":["dan"]},"11\/22\/2016":{"3375":["kelly"],"3376":["bill","rachelp"],"3380":["kathyboblitt","ben","michael"],"3504":["anne"]},"11\/23\/2016":{"3375":["rae"],"3376":["ted","gayle"],"3380":["ted","nicholas","bill"],"3504":["anne"]},"11\/28\/2016":{"3375":["dale"],"3376":["meg","dan"],"3380":["debbi","bill",null],"3504":["gayle"]},"11\/29\/2016":{"3375":["tammy"],"3376":["anastasia","nancy"],"3380":["rod","michael","mac"],"3504":["katie"]},"11\/30\/2016":{"3375":["kelly"],"3376":["keithg","megan"],"3380":["patti","kate",null],"3504":[null]},"12\/4\/2016":{"3377":["eric"],"3378":["catherine","pam"],"3381":["mac","tolkien","mario"]},"12\/5\/2016":{"3375":["sharon"],"3376":["dan","meg"],"3380":["meg","bill","debbi"],"3504":["gayle"]},"12\/6\/2016":{"3375":["dale"],"3376":["rae","meg"],"3380":["ted","meg","mac"],"3504":[null]},"12\/7\/2016":{"3379":["gail"],"3382":["kathyboblitt"]},"12\/11\/2016":{"3377":["megan"],"3378":["debbi","ben"],"3381":["megan","gayle","kathyboblitt"]},"12\/12\/2016":{"3375":["dale"],"3376":["rachelp","dan"],"3380":["rachelp","mac",null],"3504":["katie"]},"12\/13\/2016":{"3375":["kelly"],"3376":["michellemyers","meg"],"3380":["patti","meg","kate"],"3504":[null]},"12\/14\/2016":{"3375":["tammy"],"3376":["jillian","sharon"],"3380":["jillian","bill","hope"],"3504":["anne"]},"12\/18\/2016":{"3377":["pam"],"3378":["anne","gaz"],"3381":["kathyboblitt","julia","mario"]},"12\/19\/2016":{"3379":["gail"],"3382":["dan"]},"12\/20\/2016":{"3375":["sharon"],"3376":["katie","rae"],"3380":["mac","jacob","nicholas"],"3504":[null]},"12\/21\/2016":{"3375":["jennifer"],"3376":["tevah","nancy"],"3380":["amyh","michael","hope"],"3504":["gayle"]},"12\/26\/2016":{"3375":["kate"],"3376":["rebecca","elisha"],"3380":["debbi","kate","michael"],"3504":["gayle"]},"12\/27\/2016":{"3375":["tammy"],"3376":["gayle","gaz"],"3380":["ted","ben","jacob"],"3504":["anne"]},"12\/28\/2016":{"3375":["jennifer"],"3376":["anastasia","megan"],"3380":["hope","anastasia","nicholas"],"3504":["anne"]}}